llama_index/packs/secgpt/__init__.py
llama_index/packs/secgpt/hub.py
llama_index/packs/secgpt/hub_operator.py
llama_index/packs/secgpt/message.py
llama_index/packs/secgpt/permission.py
llama_index/packs/secgpt/planner.py
llama_index/packs/secgpt/sandbox.py
llama_index/packs/secgpt/sock.py
llama_index/packs/secgpt/spoke.py
llama_index/packs/secgpt/spoke_operator.py
llama_index/packs/secgpt/spoke_parser.py
llama_index/packs/secgpt/tool_importer.py
llama_index/packs/secgpt/vanilla_spoke.py
llama_index_packs_secgpt-0.3.1.dist-info/METADATA
llama_index_packs_secgpt-0.3.1.dist-info/WHEEL
llama_index_packs_secgpt-0.3.1.dist-info/licenses/LICENSE
llama_index_packs_secgpt-0.3.1.dist-info/RECORD
