Metadata-Version: 2.4
Name: llama-index-packs-secgpt
Version: 0.3.1
Summary: llama-index packs - secgpt pack
Author: Yuhao-W
License-Expression: MIT
License-File: LICENSE
Requires-Python: <4.0,>=3.9
Requires-Dist: dirtyjson<2,>=1.0.8
Requires-Dist: jsonschema<5,>=4.21.1
Requires-Dist: langchain-core<0.2,>=0.1.45
Requires-Dist: llama-index-core<0.13,>=0.12.0
Requires-Dist: llama-index-llms-openai<0.5,>=0.4.0
Requires-Dist: pyseccomp<0.2,>=0.1.2
Requires-Dist: tldextract<6,>=5.1.1
